LS_toolbox/__init__.py
LS_toolbox/clear_sim_files.py
LS_toolbox/convert.py
LS_toolbox/display.py
LS_toolbox/prepost_commands.py
LS_toolbox/read_keyfile.py
LS_toolbox/read_mesh.py
LS_toolbox/read_stl.py
LS_toolbox/write_keyfile.py
LS_toolbox/Example/Beam_3D_mesh_example.k
LS_toolbox/Example/Beam_3D_mesh_example_model.k
LS_toolbox-0.1.8.3.dist-info/METADATA
LS_toolbox-0.1.8.3.dist-info/WHEEL
LS_toolbox-0.1.8.3.dist-info/top_level.txt
LS_toolbox-0.1.8.3.dist-info/RECORD
