Metadata-Version: 2.1
Name: LS_toolbox
Version: 0.1.8.3
Summary: Toolboxes for working with LS-Dyna and LS-Prepost through python.
Home-page: 
Author: Marc Gardegaront
Author-email: marc.gardegaront@univ-eiffel.fr
Classifier: Programming Language :: Python :: 3
Classifier: License :: OSI Approved :: MIT License
Classifier: Operating System :: OS Independent
Requires-Python: >=3.6
Requires-Dist: numpy
Requires-Dist: numpy-stl
